my_temppackage123456/__init__.py
numpy/__init__.py
my_temppackage123456-0.1.1.dist-info/METADATA
my_temppackage123456-0.1.1.dist-info/WHEEL
my_temppackage123456-0.1.1.dist-info/RECORD
